MANIFEST.in
README.rst
requirements.txt
setup.py
cos_python_sdk_v5_logging.egg-info/PKG-INFO
cos_python_sdk_v5_logging.egg-info/SOURCES.txt
cos_python_sdk_v5_logging.egg-info/dependency_links.txt
cos_python_sdk_v5_logging.egg-info/requires.txt
cos_python_sdk_v5_logging.egg-info/top_level.txt
qcloud_cos/__init__.py
qcloud_cos/cos_auth.py
qcloud_cos/cos_client.py
qcloud_cos/cos_comm.py
qcloud_cos/cos_exception.py
qcloud_cos/cos_threadpool.py
qcloud_cos/demo.py
qcloud_cos/streambody.py
qcloud_cos/xml2dict.py