Metadata-Version: 1.0
Name: cos-python-sdk-v5-logging
Version: 1.0.0
Summary: cos-python-sdk-v5 for logging only
Home-page: https://www.qcloud.com/
Author: tiedu, lewzylu, channingliu
Author-email: dutie123@qq.com
License: MIT
Platform: UNKNOWN
